tiny_python/__init__.py
tiny_python/_version.py
tiny_python/constants.py
tiny_python/executor.py
tiny_python/parser.py
tiny_python-0.2.2.dist-info/METADATA
tiny_python-0.2.2.dist-info/WHEEL
tiny_python-0.2.2.dist-info/licenses/LICENSE
tiny_python-0.2.2.dist-info/RECORD
